{
  "1102071": {
    "name": "Ckreepa",
    "level": 75,
    "days_in_faction": 66
  },
  "1737122": {
    "name": "Fulgrim2",
    "level": 32,
    "days_in_faction": 70
  },
  "1978647": {
    "name": "Delldax",
    "level": 89,
    "days_in_faction": 137
  },
  "1997029": {
    "name": "Somehomelessmen",
    "level": 50,
    "days_in_faction": 141
  },
  "2224014": {
    "name": "Blazebugg",
    "level": 76,
    "days_in_faction": 70
  },
  "2291615": {
    "name": "Daany56778",
    "level": 27,
    "days_in_faction": 141
  },
  "2348322": {
    "name": "SPANJO22",
    "level": 52,
    "days_in_faction": 41
  },
  "2594774": {
    "name": "MrShenanigans",
    "level": 65,
    "days_in_faction": 23
  },
  "2792892": {
    "name": "Xevi",
    "level": 53,
    "days_in_faction": 121
  },
  "2802730": {
    "name": "datcracker420",
    "level": 90,
    "days_in_faction": 426
  },
  "2939779": {
    "name": "JaydusStrokka",
    "level": 56,
    "days_in_faction": 1022
  },
  "2967439": {
    "name": "VictoriaCicile",
    "level": 18,
    "days_in_faction": 46
  },
  "3150667": {
    "name": "CJ120",
    "level": 31,
    "days_in_faction": 80
  },
  "3157644": {
    "name": "SirJimboSliceSr",
    "level": 56,
    "days_in_faction": 148
  },
  "3163147": {
    "name": "bitek",
    "level": 55,
    "days_in_faction": 44
  },
  "3163171": {
    "name": "Kaleciatko",
    "level": 55,
    "days_in_faction": 44
  },
  "3171413": {
    "name": "xKittehxKatx",
    "level": 15,
    "days_in_faction": 148
  },
  "3251423": {
    "name": "err0r418125",
    "level": 58,
    "days_in_faction": 184
  },
  "3277325": {
    "name": "Kain_korso",
    "level": 58,
    "days_in_faction": 321
  },
  "3293671": {
    "name": "Carldica",
    "level": 69,
    "days_in_faction": 9
  },
  "3513090": {
    "name": "Squith",
    "level": 30,
    "days_in_faction": 118
  },
  "3562619": {
    "name": "Postman_",
    "level": 71,
    "days_in_faction": 407
  },
  "3563386": {
    "name": "Doomlegion",
    "level": 53,
    "days_in_faction": 385
  },
  "3599627": {
    "name": "CaptainRinny",
    "level": 57,
    "days_in_faction": 369
  },
  "3627681": {
    "name": "ZeTwilighTwizz",
    "level": 41,
    "days_in_faction": 346
  },
  "3632971": {
    "name": "Hershey54",
    "level": 21,
    "days_in_faction": 46
  },
  "3712127": {
    "name": "caits",
    "level": 26,
    "days_in_faction": 120
  },
  "3722358": {
    "name": "Deviyl",
    "level": 25,
    "days_in_faction": 117
  },
  "3727751": {
    "name": "Bobbelbo",
    "level": 40,
    "days_in_faction": 208
  },
  "3774090": {
    "name": "Jereos",
    "level": 45,
    "days_in_faction": 231
  },
  "3793607": {
    "name": "MADSCOTBASTARD",
    "level": 44,
    "days_in_faction": 9
  },
  "3796175": {
    "name": "PowerMax",
    "level": 39,
    "days_in_faction": 159
  },
  "3844859": {
    "name": "Mr_Lynch_Ryder",
    "level": 23,
    "days_in_faction": 46
  },
  "3869940": {
    "name": "Onigirli_",
    "level": 23,
    "days_in_faction": 70
  },
  "3913421": {
    "name": "Wolfylein",
    "level": 44,
    "days_in_faction": 143
  },
  "3993903": {
    "name": "PeachesCat",
    "level": 24,
    "days_in_faction": 44
  },
  "4037838": {
    "name": "MrSwift420",
    "level": 8,
    "days_in_faction": 31
  },
  "4085394": {
    "name": "BMFL85",
    "level": 9,
    "days_in_faction": 22
  },
  "2154856": {
    "name": "HowieAP",
    "level": 22,
    "days_in_faction": 4
  },
  "3783641": {
    "name": "valkyrieqt",
    "level": 29,
    "days_in_faction": 1
  },
  "4123983": {
    "name": "LuoZane",
    "level": 8,
    "days_in_faction": 0
  }
}